pandasxmledit/README.MD
pandasxmledit/__init__.py
pandasxmledit/requirements.txt
pandasxmledit/thirdparty.json
pandasxmledit-0.10.dist-info/LICENSE.rst
pandasxmledit-0.10.dist-info/METADATA
pandasxmledit-0.10.dist-info/WHEEL
pandasxmledit-0.10.dist-info/top_level.txt
pandasxmledit-0.10.dist-info/RECORD
