Metadata-Version: 2.1
Name: pandasxmledit
Version: 0.10
Summary: simplifies working with XML data by leveraging the power and flexibility of pandas DataFrames
Home-page: https://github.com/hansalemaos/pandasxmledit
Author: Johannes Fischer
Author-email: aulasparticularesdealemaosp@gmail.com
License: MIT
Keywords: xml,pandas,edit
Classifier: Development Status :: 4 - Beta
Classifier: Programming Language :: Python :: 3 :: Only
Classifier: Programming Language :: Python :: 3.10
Classifier: Topic :: Software Development :: Libraries :: Python Modules
Classifier: Topic :: Utilities
License-File: LICENSE.rst
Requires-Dist: flatten-any-dict-iterable-or-whatsoever
Requires-Dist: mymulti-key-dict
Requires-Dist: pandas
Requires-Dist: requests
Requires-Dist: xmltodict
